active_boxes/__init__.py
active_boxes/__version__.py
active_boxes/activitypub.py
active_boxes/backend.py
active_boxes/collection.py
active_boxes/content_helper.py
active_boxes/errors.py
active_boxes/httpsig.py
active_boxes/key.py
active_boxes/linked_data_sig.py
active_boxes/urlutils.py
active_boxes/webfinger.py
active_boxes-0.0.1.dev2.dist-info/LICENSE
active_boxes-0.0.1.dev2.dist-info/METADATA
active_boxes-0.0.1.dev2.dist-info/WHEEL
active_boxes-0.0.1.dev2.dist-info/RECORD
