Metadata-Version: 2.3
Name: active-boxes
Version: 0.0.1.dev2
Summary: Tiny ActivityPub framework written in Python, both database and server agnostic.
License: MIT
Author: Chaiwat Suttipongsakul
Author-email: cwt@bashell.com
Requires-Python: >=3.6.0
Classifier: Development Status :: 2 - Pre-Alpha
Classifier: License :: OSI Approved :: MIT License
Classifier: Programming Language :: Python
Classifier: Programming Language :: Python :: 3.6
Classifier: Programming Language :: Python :: 3.7
Classifier: Programming Language :: Python :: Implementation :: CPython
Classifier: Programming Language :: Python :: Implementation :: PyPy
Provides-Extra: dev
Requires-Dist: black ; extra == "dev"
Requires-Dist: codecov ; extra == "dev"
Requires-Dist: flake8 ; extra == "dev"
Requires-Dist: httpretty ; extra == "dev"
Requires-Dist: mypy ; extra == "dev"
Requires-Dist: pytest ; extra == "dev"
Requires-Dist: pytest-cov ; extra == "dev"
Project-URL: Homepage, https://github.com/cwt/active-boxes
